Metadata-Version: 2.1
Name: encurtanet
Version: 0.1.0
Author: Marcuth
Author-email: marcuth2006@gmail.com
License: MIT License
Keywords: encurtanet wrapper api
License-File: LICENCE
